orbyt/__init__.py
orbyt/analyzer.py
orbyt/cli.py
orbyt/db.py
orbyt/gmail.py
orbytx-0.1.0.dist-info/METADATA
orbytx-0.1.0.dist-info/WHEEL
orbytx-0.1.0.dist-info/entry_points.txt
orbytx-0.1.0.dist-info/top_level.txt
orbytx-0.1.0.dist-info/RECORD
