Metadata-Version: 2.4
Name: orbytx
Version: 0.1.0
Requires-Dist: typer>=0.12.3
Requires-Dist: rich>=13.7.1
Requires-Dist: google-api-python-client>=2.114.0
Requires-Dist: google-auth-oauthlib>=1.2.0
Requires-Dist: google-auth-httplib2>=0.2.0
Dynamic: requires-dist
